unfancy.py
unfancy-1.0.dist-info/WHEEL
unfancy-1.0.dist-info/METADATA
unfancy-1.0.dist-info/RECORD
