Metadata-Version: 2.1
Name: unfancy
Version: 1.0
Summary: Translate fancy text to regular text
Author-email: Ngô Ngọc Đức Huy <huyngo@disroot.org>
Classifier: Intended Audience :: Developers
Classifier: License :: OSI Approved :: Mozilla Public License 2.0 (MPL 2.0)
Classifier: Operating System :: OS Independent
Classifier: Programming Language :: Python :: 3
Classifier: Topic :: Software Development :: Libraries :: Python Modules
Classifier: Topic :: Text Processing
Classifier: Typing :: Typed
Project-URL: Home, https://git.sr.ht/~huyngo/unfancy
